<story>
	<title>Lettres min haut</title>
	<sentence>
		<word>Minuscules coupable haut</word>
	</sentence>
	<sentence>
		<word police="coupable_haut" code="ohodofohiiiihlm">abcdefghijkklm</word>
		<word police="coupable_haut" code="ooooootiiiiiiiiiiiz">nopqrstuvwxyz</word>
	</sentence>
	<sentence>
		<word police="coupable_haut" >Cas particuliers</word>
	</sentence>
	<sentence>
		<word next_value="w" police="coupable_haut" code="iii">iu</word>
		<word next_value="w" police="coupable_haut" code="iii">iv</word>
		<word next_value="w" police="coupable_haut" code="iii">ix</word>
		<word next_value="w" police="coupable_haut" code="iii">ui</word>
		<word next_value="w" police="coupable_haut" code="iii">vi</word>
		<word>coupable</word>
	</sentence>
</story>
